limitlessled_rf/__init__.py
limitlessled_rf-0.15.dist-info/LICENSE
limitlessled_rf-0.15.dist-info/METADATA
limitlessled_rf-0.15.dist-info/WHEEL
limitlessled_rf-0.15.dist-info/top_level.txt
limitlessled_rf-0.15.dist-info/RECORD
