Metadata-Version: 2.1
Name: limitlessled-rf
Version: 0.15
Summary: Python LimitlessLED via RF
Home-page: https://chiselapp.com/user/rkeene/repository/limitlessled_rf/
Author: Roy Keene
Author-email: pypi@rkeene.org
License: MIT License
Platform: UNKNOWN
Classifier: Programming Language :: Python :: 3
Classifier: License :: OSI Approved :: MIT License
Classifier: Operating System :: OS Independent
Requires-Python: >=3.6
